prisma/__init__.py
prisma/__main__.py
prisma/_async_http.py
prisma/_sync_http.py
prisma/_types.py
prisma/errors.py
prisma/http.py
prisma/http_abstract.py
prisma/jsonrpc.py
prisma/mypy.py
prisma/py.typed
prisma/utils.py
prisma/validator.py
prisma/binaries/__init__.py
prisma/binaries/binaries.py
prisma/binaries/binary.py
prisma/binaries/constants.py
prisma/binaries/engine.py
prisma/binaries/platform.py
prisma/binaries/utils.py
prisma/cli/__init__.py
prisma/cli/cli.py
prisma/cli/custom.py
prisma/cli/options.py
prisma/cli/prisma.py
prisma/cli/utils.py
prisma/cli/commands/__init__.py
prisma/cli/commands/dev.py
prisma/cli/commands/fetch.py
prisma/cli/commands/generate.py
prisma/cli/commands/version.py
prisma/engine/__init__.py
prisma/engine/errors.py
prisma/engine/utils.py
prisma/generator/__init__.py
prisma/generator/generator.py
prisma/generator/models.py
prisma/generator/types.py
prisma/generator/utils.py
prisma/generator/templates/_header.py.jinja
prisma/generator/templates/_utils.py.jinja
prisma/generator/templates/builder.py.jinja
prisma/generator/templates/client.py.jinja
prisma/generator/templates/enums.py.jinja
prisma/generator/templates/fields.py.jinja
prisma/generator/templates/http.py.jinja
prisma/generator/templates/models.py.jinja
prisma/generator/templates/partials.py.jinja
prisma/generator/templates/types.py.jinja
prisma/generator/templates/engine/query.py.jinja
prisma_client-0.2.1.dist-info/LICENSE
prisma_client-0.2.1.dist-info/METADATA
prisma_client-0.2.1.dist-info/WHEEL
prisma_client-0.2.1.dist-info/entry_points.txt
prisma_client-0.2.1.dist-info/top_level.txt
prisma_client-0.2.1.dist-info/RECORD
