Metadata-Version: 2.1
Name: prisma-client
Version: 0.2.1
Summary: Prisma Client Python is an auto-generated and fully type-safe database client
Home-page: https://github.com/RobertCraigie/prisma-client-py
Author: Robert Craigie
Author-email: robert@craigie.dev
Maintainer: Robert Craigie
License: APACHE
Project-URL: Documentation, https://prisma-client-py.readthedocs.io
Project-URL: Source, https://github.com/RobertCraigie/prisma-client-py
Project-URL: Tracker, https://github.com/RobertCraigie/prisma-client-py/issues
Keywords: orm,mysql,typing,prisma,sqlite,database,postgresql
Platform: UNKNOWN
Classifier: Development Status :: 1 - Planning
Classifier: Intended Audience :: Developers
Classifier: Typing :: Typed
Classifier: Topic :: Software Development :: Libraries :: Python Modules
Classifier: Topic :: Database :: Database Engines/Servers
Classifier: License :: OSI Approved :: Apache Software License
Classifier: Programming Language :: Python :: 3.6
Classifier: Programming Language :: Python :: 3.7
Classifier: Programming Language :: Python :: 3.8
Classifier: Programming Language :: Python :: 3.9
Requires-Python: >=3
Provides-Extra: dev
Provides-Extra: docs
Provides-Extra: all
License-File: LICENSE
